roman_arabic_numerals/conv.py
roman_arabic_numerals-0.8.0.dist-info/LICENSE
roman_arabic_numerals-0.8.0.dist-info/METADATA
roman_arabic_numerals-0.8.0.dist-info/WHEEL
roman_arabic_numerals-0.8.0.dist-info/top_level.txt
roman_arabic_numerals-0.8.0.dist-info/RECORD
