Metadata-Version: 2.1
Name: roman-arabic-numerals
Version: 0.8.0
Summary: Roman numerals converting
Author: s0urce
Author-email: boyarkin.gleb@gmail.com
License-File: LICENSE
